fixingbugstool/__init__.py
fixingbugstool-0.0.3.dist-info/LICENSE.txt
fixingbugstool-0.0.3.dist-info/METADATA
fixingbugstool-0.0.3.dist-info/WHEEL
fixingbugstool-0.0.3.dist-info/top_level.txt
fixingbugstool-0.0.3.dist-info/RECORD
