Metadata-Version: 2.1
Name: fixingbugstool
Version: 0.0.3
Summary: A tool for tracking bugs and finding solutions
Home-page: UNKNOWN
Author: rtyque
Author-email: 3hinney@gmail.com
License: UNKNOWN
Platform: UNKNOWN
Classifier: Programming Language :: Python :: 3
Classifier: License :: OSI Approved :: MIT License
Classifier: Operating System :: OS Independent
License-File: LICENSE.txt
